README.md
setup.py
bin/womgc
docs/.DS_Store
womg_core/__init__.py
womg_core/__main__.py
womg_core/propagation.py
womg_core.egg-info/PKG-INFO
womg_core.egg-info/SOURCES.txt
womg_core.egg-info/dependency_links.txt
womg_core.egg-info/entry_points.txt
womg_core.egg-info/requires.txt
womg_core.egg-info/top_level.txt
womg_core/diffusion/__init__.py
womg_core/diffusion/diffusion_model.py
womg_core/diffusion/tlt.py
womg_core/network/__init__.py
womg_core/network/network_model.py
womg_core/network/tlt_network_model.py
womg_core/network/tn.py
womg_core/topic/__init__.py
womg_core/topic/lda.py
womg_core/topic/tlt_topic_model.py
womg_core/topic/topic_model.py
womg_core/utils/__init__.py
womg_core/utils/distributions.py
womg_core/utils/saver.py
womg_core/utils/utility_functions.py
womgdata/docs/demo_corpus/AP880212-0078.txt
womgdata/docs/demo_corpus/AP880213-0055.txt
womgdata/docs/training_corpus/w_acad_1990.txt
womgdata/docs/training_corpus/w_acad_1991.txt
womgdata/docs/training_corpus/w_acad_1992.txt
womgdata/docs/training_corpus/w_acad_1993.txt
womgdata/docs/training_corpus/w_acad_1994.txt
womgdata/docs/training_corpus/w_acad_1995.txt
womgdata/docs/training_corpus/w_acad_1996.txt
womgdata/docs/training_corpus/w_acad_1997.txt
womgdata/docs/training_corpus/w_acad_1998.txt
womgdata/docs/training_corpus/w_acad_1999.txt
womgdata/docs/training_corpus/w_acad_2000.txt
womgdata/docs/training_corpus/w_acad_2001.txt
womgdata/docs/training_corpus/w_acad_2002.txt
womgdata/docs/training_corpus/w_acad_2003.txt
womgdata/docs/training_corpus/w_acad_2004.txt
womgdata/docs/training_corpus/w_acad_2005.txt
womgdata/docs/training_corpus/w_acad_2006.txt
womgdata/docs/training_corpus/w_acad_2007.txt
womgdata/docs/training_corpus/w_acad_2008.txt
womgdata/docs/training_corpus/w_acad_2009.txt
womgdata/docs/training_corpus/w_acad_2010.txt
womgdata/docs/training_corpus/w_acad_2011.txt
womgdata/docs/training_corpus/w_acad_2012.txt
womgdata/docs/training_corpus/w_fic_1990.txt
womgdata/docs/training_corpus/w_fic_1991.txt
womgdata/docs/training_corpus/w_fic_1992.txt
womgdata/docs/training_corpus/w_fic_1993.txt
womgdata/docs/training_corpus/w_fic_1994.txt
womgdata/docs/training_corpus/w_fic_1995.txt
